kakaosb/__init__.py
kakaosb/builder.py
kakaosb/buttons.py
kakaosb/cards.py
kakaosb/commons.py
kakaosb/simples.py
kakaosb/templates.py
kakaosb-1.0.0.dist-info/LICENSE
kakaosb-1.0.0.dist-info/METADATA
kakaosb-1.0.0.dist-info/WHEEL
kakaosb-1.0.0.dist-info/top_level.txt
kakaosb-1.0.0.dist-info/RECORD
