Metadata-Version: 2.1
Name: kakaosb
Version: 1.0.0
Summary: kakao i openbuilder skill response template builder ⚒ for python 🐍
Home-page: https://github.com/taeminlee/kakao-skill-template-builder
Author: Taemin Lee
Author-email: persuade@gmail.com
License: UNKNOWN
Platform: UNKNOWN
Classifier: Programming Language :: Python
Requires-Python: >=3.6
